atomicloop/__init__.py
atomicloop-1.0.0.dist-info/METADATA
atomicloop-1.0.0.dist-info/RECORD
atomicloop-1.0.0.dist-info/WHEEL
atomicloop-1.0.0.dist-info/top_level.txt
