Metadata-Version: 2.1
Name: atomicloop
Version: 1.0.0
Summary: Create atomic loop iterations (let the iteration finish even when interrupted)
Home-page: https://github.com/kysely/atomicloop
Author: Radek Kysely
Author-email: kyselyradek@gmail.com
License: MIT
Download-URL: https://pypi.org/project/atomicloop/
Keywords: atomic,linearizable,undivisible,uninterruptible,atomic loop,atomic block,atomic operation,delayed interrupt,delayed keyboardinterrupt,keyboardinterrupt,SIGINT,SIGTERM
Platform: UNKNOWN
Classifier: Development Status :: 5 - Production/Stable
Classifier: Intended Audience :: Developers
Classifier: License :: OSI Approved :: MIT License
Classifier: Natural Language :: English
Classifier: Operating System :: OS Independent
Classifier: Programming Language :: Python :: 3
Classifier: Topic :: Software Development :: Libraries :: Python Modules
